appsdk/__init__.py
appsdk/sample.py
appsdk/welcome.py
appsdk-0.1.0.dist-info/METADATA
appsdk-0.1.0.dist-info/WHEEL
appsdk-0.1.0.dist-info/RECORD
