Metadata-Version: 2.1
Name: appsdk
Version: 0.1.0
Summary: app-registry-sdk
Author: Anjaiah Methuku
Author-email: anjaiahspr@gmail.com
Requires-Python: >=3.11,<4.0
Classifier: Programming Language :: Python :: 3
Classifier: Programming Language :: Python :: 3.11
Classifier: Programming Language :: Python :: 3.12
Requires-Dist: requests (>=2.32.3,<3.0.0)
